<?xml version="1.0" encoding="UTF-8"?>

<devices>
    <!--<device>-->
        <!--<manufacturer>htc</manufacturer>&lt;!&ndash;设备制造厂商  全部小写中间没有空格&ndash;&gt;-->
		<!--<model>htcones</model>&lt;!&ndash;设备型号 全部小写中间没有空格&ndash;&gt;-->
		<!--<sdk_leve>-1</sdk_leve>	&lt;!&ndash;手机对应SDK的版本号 &ndash;&gt;-->
		<!--<audio_mode>2</audio_mode>&lt;!&ndash;0对应的是AudioManager.MODE_NORMAL,2对应的是AudioManager.MODE_IN_CALL,3对应的是AudioManager.MODE_IN_COMMUNICATION&ndash;&gt;-->
    <!--</device>-->
    <!--<device>-->
        <!--<manufacturer>xiaomi</manufacturer>&lt;!&ndash;设备制造厂商  全部小写中间没有空格&ndash;&gt;-->
        <!--<model>htcones</model>&lt;!&ndash;设备型号 全部小写中间没有空格&ndash;&gt;-->
        <!--<sdk_leve>-1</sdk_leve>	&lt;!&ndash;手机对应SDK的版本号 &ndash;&gt;-->
        <!--<audio_mode>2</audio_mode>&lt;!&ndash;0对应的是AudioManager.MODE_NORMAL,2对应的是AudioManager.MODE_IN_CALL,3对应的是AudioManager.MODE_IN_COMMUNICATION&ndash;&gt;-->
    <!--</device>-->
</devices>